json_serializer/__init__.py
json_serializer/constants.py
json_serializer/json_serializer.py
serializer/__init__.py
serializer/constants.py
serializer/serializer.py
serializer_factory/__init__.py
serializer_factory/serializer_factory.py
xml_serializer/__init__.py
xml_serializer/constants.py
xml_serializer/xml_serializer.py
serializer_ByKaxxa-0.1.0.dist-info/METADATA
serializer_ByKaxxa-0.1.0.dist-info/WHEEL
serializer_ByKaxxa-0.1.0.dist-info/top_level.txt
serializer_ByKaxxa-0.1.0.dist-info/RECORD
