Metadata-Version: 2.1
Name: serializer-ByKaxxa
Version: 0.1.0
Summary: JSON / XML serializer
Author: Kakhnouski Eugene
Author-email: Kaxxa2927@gmail.com
License: MIT
Classifier: Programming Language :: Python
Classifier: Operating System :: OS Independent
Requires-Dist: regex
